lsg_converter/__init__.py
lsg_converter/conversion_utils.py
lsg_converter/converter.py
lsg_converter/dummy_conversion.py
lsg_converter/albert/__init__.py
lsg_converter/albert/convert_albert_checkpoint.py
lsg_converter/albert/modeling_lsg_albert.py
lsg_converter/attention_layers/__init__.py
lsg_converter/attention_layers/lsg_self_attention.py
lsg_converter/bart/__init__.py
lsg_converter/bart/convert_bart_checkpoint.py
lsg_converter/bart/modeling_lsg_bart.py
lsg_converter/barthez/__init__.py
lsg_converter/barthez/convert_barthez_checkpoint.py
lsg_converter/barthez/modeling_lsg_barthez.py
lsg_converter/bert/__init__.py
lsg_converter/bert/convert_bert_checkpoint.py
lsg_converter/bert/modeling_lsg_bert.py
lsg_converter/camembert/__init__.py
lsg_converter/camembert/convert_camembert_checkpoint.py
lsg_converter/camembert/modeling_lsg_camembert.py
lsg_converter/distilbert/__init__.py
lsg_converter/distilbert/convert_distilbert_checkpoint.py
lsg_converter/distilbert/modeling_lsg_distilbert.py
lsg_converter/electra/__init__.py
lsg_converter/electra/convert_electra_checkpoint.py
lsg_converter/electra/modeling_lsg_electra.py
lsg_converter/mbart/__init__.py
lsg_converter/mbart/convert_mbart_checkpoint.py
lsg_converter/mbart/modeling_lsg_mbart.py
lsg_converter/pegasus/__init__.py
lsg_converter/pegasus/convert_pegasus_checkpoint.py
lsg_converter/pegasus/modeling_lsg_pegasus.py
lsg_converter/roberta/__init__.py
lsg_converter/roberta/convert_roberta_checkpoint.py
lsg_converter/roberta/modeling_lsg_roberta.py
lsg_converter/xlm_roberta/__init__.py
lsg_converter/xlm_roberta/convert_xlm_roberta_checkpoint.py
lsg_converter/xlm_roberta/modeling_lsg_xlm_roberta.py
lsg_converter-0.1.9.dist-info/LICENSE.txt
lsg_converter-0.1.9.dist-info/METADATA
lsg_converter-0.1.9.dist-info/WHEEL
lsg_converter-0.1.9.dist-info/top_level.txt
lsg_converter-0.1.9.dist-info/RECORD
