Metadata-Version: 2.1
Name: lsg-converter
Version: 0.1.9
Summary: To convert HuggingFace models to their LSG variant
Home-page: https://github.com/ccdv-ai/convert_checkpoint_to_lsg
Author: Charles Condevaux
Author-email: charles.condevaux@gmail.com
Classifier: Programming Language :: Python :: 3
Classifier: License :: OSI Approved :: MIT License
Classifier: Operating System :: OS Independent
Requires-Python: >=3.8
License-File: LICENSE.txt
Requires-Dist: transformers >=4.36.1
Requires-Dist: torch >=1.8
